xcore_framework/__init__.py
xcore_framework/__main__.py
xcore_framework/main.py
xcore_framework/__pycache__/__init__.cpython-311.pyc
xcore_framework/__pycache__/__main__.cpython-311.pyc
xcore_framework/config/__init__.py
xcore_framework/config/banner.py
xcore_framework/config/db.py
xcore_framework/config/env.py
xcore_framework/config/formatting.py
xcore_framework/config/__pycache__/__init__.cpython-311.pyc
xcore_framework/config/__pycache__/banner.cpython-311.pyc
xcore_framework/config/__pycache__/db.cpython-311.pyc
xcore_framework/config/__pycache__/env.cpython-311.pyc
xcore_framework/config/__pycache__/formatting.cpython-311.pyc
xcore_framework/config/i18n/__init__.py
xcore_framework/config/i18n/i18n_manager.py
xcore_framework/config/i18n/__pycache__/__init__.cpython-311.pyc
xcore_framework/config/i18n/__pycache__/i18n_manager.cpython-311.pyc
xcore_framework/config/i18n/de/config.json
xcore_framework/config/i18n/de/creative_ascii_qrcode.json
xcore_framework/config/i18n/de/database.json
xcore_framework/config/i18n/de/gui.json
xcore_framework/config/i18n/de/header.json
xcore_framework/config/i18n/de/help.json
xcore_framework/config/i18n/de/info.json
xcore_framework/config/i18n/de/main.json
xcore_framework/config/i18n/de/module.json
xcore_framework/config/i18n/de/options.json
xcore_framework/config/i18n/de/scanner_nmap.json
xcore_framework/config/i18n/de/setpoint_cli.json
xcore_framework/config/i18n/de/setpoint_gui.json
xcore_framework/config/i18n/de/system.json
xcore_framework/config/i18n/de/template_modul.json
xcore_framework/config/i18n/en/config.json
xcore_framework/config/i18n/en/creative_ascii_qrcode.json
xcore_framework/config/i18n/en/database.json
xcore_framework/config/i18n/en/gui.json
xcore_framework/config/i18n/en/header.json
xcore_framework/config/i18n/en/help.json
xcore_framework/config/i18n/en/info.json
xcore_framework/config/i18n/en/main.json
xcore_framework/config/i18n/en/module.json
xcore_framework/config/i18n/en/options.json
xcore_framework-0.1.0a5.dist-info/licenses/LICENSE
xcore_framework-0.1.0a5.dist-info/METADATA
xcore_framework-0.1.0a5.dist-info/WHEEL
xcore_framework-0.1.0a5.dist-info/entry_points.txt
xcore_framework-0.1.0a5.dist-info/top_level.txt
xcore_framework-0.1.0a5.dist-info/RECORD
