Metadata-Version: 2.4
Name: xcore_framework
Version: 0.1.0a5
Summary: CLI- und Webframework für modulare Anwendungen mit interaktiver Shell, GUI und Webinterface.
Author-email: "x404bjrn (Björn Häusermann)" <void@insomnialegion.xyz>
License: MIT License
Project-URL: Homepage, https://github.com/x404bjrn/XCORE
Classifier: Development Status :: 3 - Alpha
Classifier: Intended Audience :: Developers
Classifier: Topic :: Software Development :: Libraries :: Application Frameworks
Classifier: License :: OSI Approved :: MIT License
Classifier: Programming Language :: Python :: 3.10
Classifier: Programming Language :: Python :: 3.11
Classifier: Operating System :: OS Independent
Classifier: Environment :: Console
Classifier: Environment :: Web Environment
Classifier: Framework :: Flask
Classifier: Natural Language :: English
Classifier: Natural Language :: German
Requires-Python: >=3.10
License-File: LICENSE
Requires-Dist: setuptools~=78.1.0
Requires-Dist: python-dotenv~=1.1.0
Requires-Dist: Flask~=3.1.1
Requires-Dist: Flask-Login~=0.6.3
Requires-Dist: Werkzeug~=3.1.3
Requires-Dist: flask-cors~=6.0.0
Requires-Dist: colorama~=0.4.6
Requires-Dist: pytest~=8.4.0
Requires-Dist: qrcode>=8.2
Requires-Dist: pillow~=11.2.1
Requires-Dist: cryptography~=45.0.4
Requires-Dist: flask-sqlalchemy~=3.1.1
Requires-Dist: click>=8.1.8
Requires-Dist: gunicorn>=23.0.0
Requires-Dist: waitress>=3.0.2
Requires-Dist: httpx>=0.28.0
Requires-Dist: httpcore>=1.0.6
Requires-Dist: h11>=0.16.0
Requires-Dist: translate>=3.6.1
Requires-Dist: tox>=4.27.0
Provides-Extra: dev
Requires-Dist: pytest; extra == "dev"
Requires-Dist: flake8; extra == "dev"
Requires-Dist: black; extra == "dev"
Requires-Dist: mypy; extra == "dev"
Dynamic: license-file
